Metadata-Version: 1.0
Name: dsn39-probability
Version: 1.2
Summary: Gaussian distributions and Binomial distributions
Home-page: UNKNOWN
Author: Joshua Agba
Author-email: joshua.agba.aj@gmail.com
License: UNKNOWN
Platform: UNKNOWN
